calcpkq/__init__.py
calcpkq/geometry.py
calcpkq/operration.py
calcpkq/test.py
calcpkq-0.1.dist-info/DESCRIPTION.rst
calcpkq-0.1.dist-info/METADATA
calcpkq-0.1.dist-info/RECORD
calcpkq-0.1.dist-info/WHEEL
calcpkq-0.1.dist-info/metadata.json
calcpkq-0.1.dist-info/top_level.txt
