Metadata-Version: 2.0
Name: calcpkq
Version: 0.1
Summary: package_upload_test
Home-page: https://github.com/doorBW/pypi_deploy_test
Author: byeongsun
Author-email: ii7891@naver.com
License: UNKNOWN
Download-URL: https://github.com/doorBW/pypi_deploy_test/archive/master.zip
Keywords: pypi deploy
Platform: UNKNOWN
Classifier: Programming Language :: Python :: 3
Classifier: Programming Language :: Python :: 3.2
Classifier: Programming Language :: Python :: 3.3
Classifier: Programming Language :: Python :: 3.4
Classifier: Programming Language :: Python :: 3.5
Classifier: Programming Language :: Python :: 3.6
Classifier: Programming Language :: Python :: 3.7
Requires-Python: >=3
